.annotation j2cc/Nativeify {}
.super java/lang/Object
.class Test {


	.method <init> ()V {
		parameters: { this },
		code: {
			aload this
			invokespecial java/lang/Object.<init> ()V
			return 
		}
	}

	.method public static main ([Ljava/lang/String;)V {
		parameters: { p0 },
		code: {
			getstatic java/lang/System.out Ljava/io/PrintStream;
			ldc 10.0D
			d2f 
			invokevirtual java/io/PrintStream.println (F)V
			getstatic java/lang/System.out Ljava/io/PrintStream;
			ldc 10.4D
			d2i 
			invokevirtual java/io/PrintStream.println (I)V
			getstatic java/lang/System.out Ljava/io/PrintStream;
			ldc -10.4D
			d2i 
			invokevirtual java/io/PrintStream.println (I)V
			getstatic java/lang/System.out Ljava/io/PrintStream;
			ldc 10.0D
			d2l 
			invokevirtual java/io/PrintStream.println (J)V
			getstatic java/lang/System.out Ljava/io/PrintStream;
			ldc 9.5F
			f2d 
			invokevirtual java/io/PrintStream.println (D)V
			getstatic java/lang/System.out Ljava/io/PrintStream;
			ldc 9.4F
			f2i 
			invokevirtual java/io/PrintStream.println (I)V
			getstatic java/lang/System.out Ljava/io/PrintStream;
			ldc -9.4F
			f2i 
			invokevirtual java/io/PrintStream.println (I)V
			getstatic java/lang/System.out Ljava/io/PrintStream;
			ldc -9.4F
			f2l 
			invokevirtual java/io/PrintStream.println (J)V
			getstatic java/lang/System.out Ljava/io/PrintStream;
			sipush 200
			i2b 
			invokevirtual java/io/PrintStream.println (I)V
			getstatic java/lang/System.out Ljava/io/PrintStream;
			bipush 93
			i2c 
			invokevirtual java/io/PrintStream.println (C)V
			getstatic java/lang/System.out Ljava/io/PrintStream;
			bipush 123
			i2d 
			invokevirtual java/io/PrintStream.println (D)V
			getstatic java/lang/System.out Ljava/io/PrintStream;
			bipush 123
			i2f 
			invokevirtual java/io/PrintStream.println (F)V
			getstatic java/lang/System.out Ljava/io/PrintStream;
			bipush 123
			i2l 
			invokevirtual java/io/PrintStream.println (J)V
			getstatic java/lang/System.out Ljava/io/PrintStream;
			ldc 90000
			i2s 
			invokevirtual java/io/PrintStream.println (I)V
			getstatic java/lang/System.out Ljava/io/PrintStream;
			ldc 123L
			l2d 
			invokevirtual java/io/PrintStream.println (D)V
			getstatic java/lang/System.out Ljava/io/PrintStream;
			ldc 123L
			l2f 
			invokevirtual java/io/PrintStream.println (F)V
			getstatic java/lang/System.out Ljava/io/PrintStream;
			ldc 5473857893L
			l2i 
			invokevirtual java/io/PrintStream.println (I)V
			return 
		}
	}

}